{"files":{"packages/mcp-server/.turbo/turbo-build.log":{"size":6,"mtime_nanos":1783054280498942800,"mode":420,"is_dir":false},"packages/mcp-server/dist/index.d.ts":{"size":29,"mtime_nanos":1783054280420886500,"mode":420,"is_dir":false},"packages/mcp-server/dist/server.js":{"size":6604,"mtime_nanos":1783054280407882900,"mode":420,"is_dir":false},"packages/mcp-server/dist":{"size":0,"mtime_nanos":0,"mode":0,"is_dir":true},"packages/mcp-server/dist/index.js":{"size":29,"mtime_nanos":1783054280418900500,"mode":420,"is_dir":false},"packages/mcp-server/dist/server.d.ts":{"size":822,"mtime_nanos":1783054280416883800,"mode":420,"is_dir":false}},"order":["packages/mcp-server/.turbo/turbo-build.log","packages/mcp-server/dist","packages/mcp-server/dist/index.d.ts","packages/mcp-server/dist/index.js","packages/mcp-server/dist/server.d.ts","packages/mcp-server/dist/server.js"]}